<?xml version="1.0" encoding="UTF-8"?>
<treatment>
  <meta>
    <source>
      <author>Gray</author>
      <date>1950</date>
    </source>
    <processed_by>
      <processor>
        <date>2014/01/30 14:07:49</date>
        <software type="format_conversion" version="f0a80a8516a06e51224d01314403eb26d60f881d">Text2XML</software>
        <operator>Hong, Cui</operator>
      </processor>
    </processed_by>
  </meta>
  <taxon_identification status="ACCEPTED">
    <genus_name>rubus</genus_name>
    <species_name>pubescens</species_name>
    <species_authority>raf.</species_authority>
    <taxon_hierarchy>family rosaceae;tribe rubeae;genus rubus;subgenus cylactis;species pubescens;</taxon_hierarchy>
  </taxon_identification>
  <number>2</number>
  <description type="morphology">Stems slender, trailing or loosely ascending, bearing erect herbaceous flowering branches 1-4 dm. high, slightly pubescent above, the vegetative shoots much prolonged and ending in flagelliform rooting tips; leaves pedately 3- or 5-foliolate, membranaceous, opaque; the central leaflet rhombic-ovate to -lanceolate, tapering about equally to the acute apex and base, coarsely and doubly serrate, glabrous or nearly so, 4-10 cm. long; flowers 1-7; calyx-lobes 3-7 (-10) mm. long, linear; petals white or pale pink, or deep roseate in forma roseiflorus (Peck) House (rose-flowered), erect, 6-10 mm. long, 1.5-3 mm. broad; fruit dark red, only tardily separating from the spongy receptacle, the richly juicy drupelets large. (R. triflorus Richards.; R. americanus Britt.)</description>
  <discussion>Hybridizes with no. 3.</discussion>
</treatment>

