<?xml version="1.0" encoding="UTF-8"?>
<treatment>
  <meta>
    <source>
      <author>Gray</author>
      <date>1950</date>
    </source>
    <processed_by>
      <processor>
        <date>2014/01/30 14:07:50</date>
        <software type="format_conversion" version="f0a80a8516a06e51224d01314403eb26d60f881d">Text2XML</software>
        <operator>Hong, Cui</operator>
      </processor>
    </processed_by>
  </meta>
  <taxon_identification status="ACCEPTED">
    <genus_name>rubus</genus_name>
    <species_name>latifoliolus</species_name>
    <species_authority>bailey</species_authority>
    <taxon_hierarchy>family rosaceae;tribe rubeae;genus rubus;subgenus eubatus;section arguti;species latifoliolus;</taxon_hierarchy>
  </taxon_identification>
  <number>189</number>
  <description type="morphology">Primocanes arching, their drooping and finally tip-trailing branches and branchlets forming mounds about 1 m. high, terete, with subacicular prickles 2-3 mm. long; primocane-leaves with very prickly petioles and petiolules; terminal leaflet broadly cordate-ovate, abruptly acuminate, closely double-serrate, glabrous above, sparsely 'pilose beneath, the ribs prominent beneath; racemiform corymb very leafy-bracted, all the bristly pedicels overtopped by the large bracts; simple upper bracts broadly ovate, lobulate; calyx-lobes tardily reflexed; fruit subglobose, small, seedy.</description>
  <discussion>Perhaps better placed in Section Tholiformes.</discussion>
</treatment>

